params.vh
// Largura de dados e endereço
`define DATA_WIDTH 32
`define ADDR_WIDTH 32

// Definições da memoria de instruções
`define INST_MEM_DEPTH 256
`define INST_MEM_FILE "../../program.bin"

risc_v_blocks/instruction_memory/instruction_memory.v
`include "../../params.vh"

module instruction_memory (
  input  [`ADDR_WIDTH - 1:0] read_address,
  output [`DATA_WIDTH - 1:0] instruction_data
);
  // Cria um banco de registradores
  reg [`DATA_WIDTH - 1:0] memory [0:`INST_MEM_DEPTH - 1];

  initial begin
    // Carrega o arquivo contendo o programa para a memoria de intruções
    $readmemb(`INST_MEM_FILE, memory);
  end

  // Atribui o valor da memória ao dado de instrução
  assign instruction_data = memory[read_address >> 2'd2];

endmodule

risc_v_blocks/instruction_memory/instruction_memory_tb.v
`timescale 1ps / 1ps
`include "../../params.vh"

module instruction_memory_tb;

  reg [`ADDR_WIDTH:0] addr;
  wire [`DATA_WIDTH:0] instr;

  instruction_memory uut (
    .read_address(addr),
    .instruction_data(instr)
  );

  integer i;

  initial begin
    $dumpfile("instruction_memory_tb.vcd");
    $dumpvars(0, instruction_memory_tb);
    

    for (i = 0; i < 10; i = i + 1) begin
      addr = i * 4;
      #10;
      $display("Endereco: %d, Instrucao: %b", addr, instr);
    end
    
    #10 $finish;
  end

endmodule

risc_v_blocks/instruction_memory/instruction_memory_tb.vcd
$date
	Sat Jul 05 22:26:59 2025
$end
$version
	Icarus Verilog
$end
$timescale
	1ps
$end
$scope module instruction_memory_tb $end
$var wire 33 ! instr [32:0] $end
$var reg 33 " addr [32:0] $end
$var integer 32 # i [31:0] $end
$scope module uut $end
$var wire 32 $ instruction_data [31:0] $end
$var wire 32 % read_address [31:0] $end
$upscope $end
$upscope $end
$enddefinitions $end
$comment Show the parameter values. $end
$dumpall
$end
#0
$dumpvars
b0 %
b10010011 $
b0 #
b0 "
b10010011 !
$end
#10
b100000001000100010011 !
b100000001000100010011 $
b100 %
b100 "
b1 #
#20
b1000001000000110110011 !
b1000001000000110110011 $
b1000 %
b1000 "
b10 #
#30
b1100010000000100010011 !
b1100010000000100010011 $
b1100 %
b1100 "
b11 #
#40
b0xxxxxxxxxxxxxxxxxxxxxxxxxxxxxxxx !
bx $
b10000 %
b10000 "
b100 #
#50
b10100 %
b10100 "
b101 #
#60
b11000 %
b11000 "
b110 #
#70
b11100 %
b11100 "
b111 #
#80
b100000 %
b100000 "
b1000 #
#90
b100100 %
b100100 "
b1001 #
#100
b1010 #
