risc_v_blocks/alu/alu.v
// 000 - ADD
// 001 - SUB
// 010 - AND
// 011 - OR
// 100 - XOR
// 101 - SLL
// 110 - SRL


module alu(
  input [31:0] op_a,
  input [31:0] op_b,
  input [3:0] alu_op,

  output reg [31:0] result,
  output reg zero
);
  always @(*) begin
    case (alu_op)
      4'b0000: result = op_a + op_b;
      4'b0001: result = op_a - op_b;
      4'b0010: result = op_a & op_b;
      4'b0011: result = op_a | op_b;
      4'b0100: result = op_a ^ op_b;
      4'b0101: result = op_a << op_b[4:0];
      4'b0110: result = op_a >> op_b[4:0];
      default: result = 32'b0;
    endcase
    zero = (result == 32'b0) ? 1 : 0;
  end

endmodule

risc_v_blocks/alu/alu_tb.v
`timescale 1ps / 1ps

module alu_tb ();
  reg [31:0] op_a;
  reg [31:0] op_b;
  reg [3:0] alu_op;

  wire [31:0] result;
  wire zero;

  alu uut(
    .op_a(op_a),
    .op_b(op_b),
    .alu_op(alu_op),
    .result(result),
    .zero(zero)
  );

  initial begin
    $dumpfile("alu_tb.vcd");
    $dumpvars(0, alu_tb);

    op_a = 32'd50;
    op_b = 32'd20;
    alu_op = 4'b0000;

    #10
    $display("50 + 20 = %d (70), zero: %d", result, zero);
    #5

    alu_op = 4'b0001;
    #10
    $display("50 - 20 = %d (30), zero: %d", result, zero);

    #5
    alu_op = 4'b0010;
    #10
    $display("===== AND =====");
    $display("%b", op_a);
    $display("%b", op_b);
    $display("%b", result);

    #5
    alu_op = 4'b0011;
    #10
    $display("===== OR =====");
    $display("%b", op_a);
    $display("%b", op_b);
    $display("%b", result);

    #5
    alu_op = 4'b0100;
    #10
    $display("===== XOR =====");
    $display("%b", op_a);
    $display("%b", op_b);
    $display("%b", result);
    
    #5
    alu_op = 4'b0101;
    op_b = 32'd3;
    #10
    $display("===== sll =====");
    $display("%b", op_a);
    $display("%b", result);
    
    #5
    alu_op = 4'b0110;
    op_b = 32'd3;
    #10
    $display("===== sll =====");
    $display("%b", op_a);
    $display("%b", result);

    alu_op = 4'b0001;
    op_b = 32'd50;
    op_a = 32'd50;
    #10
    $display("===== zero =====");
    $display("50 - 50 = %d , zero: %d", result, zero);
    #5

    #20 $finish;
  end 

endmodule

risc_v_blocks/alu/alu_tb.vcd
$date
	Sat Jul 05 20:00:39 2025
$end
$version
	Icarus Verilog
$end
$timescale
	1ps
$end
$scope module alu_tb $end
$var wire 1 ! zero $end
$var wire 32 " result [31:0] $end
$var reg 4 # alu_op [3:0] $end
$var reg 32 $ op_a [31:0] $end
$var reg 32 % op_b [31:0] $end
$scope module uut $end
$var wire 4 & alu_op [3:0] $end
$var wire 32 ' op_a [31:0] $end
$var wire 32 ( op_b [31:0] $end
$var reg 32 ) result [31:0] $end
$var reg 1 ! zero $end
$upscope $end
$upscope $end
$enddefinitions $end
$comment Show the parameter values. $end
$dumpall
$end
#0
$dumpvars
b1000110 )
b10100 (
b110010 '
b0 &
b10100 %
b110010 $
b0 #
b1000110 "
0!
$end
#15
b11110 "
b11110 )
b1 #
b1 &
#30
b10000 "
b10000 )
b10 #
b10 &
#45
b110110 "
b110110 )
b11 #
b11 &
#60
b100110 "
b100110 )
b100 #
b100 &
#75
b110010000 "
b110010000 )
b11 %
b11 (
b101 #
b101 &
#90
b110 "
b110 )
b110 #
b110 &
#100
1!
b0 "
b0 )
b110010 %
b110010 (
b1 #
b1 &
