params.vh
// Largura de dados e endereço
`define DATA_WIDTH  32
`define ADDR_WIDTH  32

`define ZERO        32'b0;

// Definições da memoria de instruções
`define INST_MEM_DEPTH 256
`define INST_MEM_FILE "../../program.bin"

// Definições do branco de registradores
`define NUM_REGISTERS 32
`define REG_ADDR_WIDTH 5 // log_2(NUM_REGISTERS)

// Definições da ALU
`define ALU_OP_WIDTH = 4

// operações da ALU
`define ALU_ADD   4'b0000
`define ALU_SUB   4'b0001
`define ALU_AND   4'b0010
`define ALU_OR    4'b0011
`define ALU_XOR   4'b0100
`define ALU_SLL   4'b0101
`define ALU_SRL   4'b0110

// Definições da unidade de controle

// pag 126
`define OPCODE_R_TYPE  7'b0110011
`define OPCODE_I_TYPE  7'b0010011
`define OPCODE_LOAD    7'b0000011
`define OPCODE_STORE   7'b0100011
`define OPCODE_BRANCH  7'b1100111

// Definição da memoria de dados
`define DMEM_DEPTH   256 
`define DATA_FILE    "../../data.bin"

risc_v_blocks/data_memory/data_memory.v
`include "../../params.vh"

module data_memory (
  input clk,
  input MemWrite,
  input MemRead,

  input [`ADDR_WIDTH-1:0] address,
  input [`DATA_WIDTH-1:0] write_data,

  output [`DATA_WIDTH-1:0] read_data
);
  reg [`DATA_WIDTH-1:0] memory[`DMEM_DEPTH-1:0];

  assign read_data = memory[address >> 2'd2];

  always @(posedge clk) begin
    if (MemWrite) begin
      memory[address >> 2'd2] <= write_data;
    end
  end
endmodule

risc_v_blocks/data_memory/data_memory_tb.v
`timescale 1ps / 1ps
`include "../../params.vh"

module data_memory_tb;
  reg clk = 0;
  always #5 clk = ~clk;

  reg MemWrite;
  reg MemRead;
  reg [`ADDR_WIDTH-1:0] address;
  reg [`DATA_WIDTH-1:0] write_data;

  wire [`DATA_WIDTH-1:0] read_data;

  data_memory uut (
    .clk(clk),
    .MemWrite(MemWrite),
    .MemRead(MemRead),
    .address(address),
    .write_data(write_data),
    .read_data(read_data)
  );

  initial begin
    $dumpfile("data_memory_tb.vcd");
    $dumpvars(0, data_memory_tb);

    MemWrite = 0;
    MemRead = 0;
    address = 32'd0;
    write_data = 32'd0;
    
    #10
    
    // Salvando dados na memoria
    MemWrite = 1'b1;

    address = 32'd4;
    write_data = 32'hAAAAAAAA;
    #10

    address = 32'd8;
    write_data = 32'hBBBBBBBB;
    #10
    
    MemWrite = 1'b0;
    #10

    // Lendo dados da memoria
    MemRead = 1;
    
    address = 32'd4;
    #5;
    $display("esperado: %d, Valor: %h, esperado: AAAAAAAA)", address, read_data);

    address = 32'd8;
    #5;
    $display("esperado: %d, Valor: %h, esperado: BBBBBBBB)", address, read_data);

    address = 32'd12;
    #5;
    $display("esperado: %d, Valor: %h)", address, read_data);
    
    #10;$finish;
  end

endmodule

risc_v_blocks/data_memory/data_memory_tb.vcd
$date
	Sun Jul 06 00:21:44 2025
$end
$version
	Icarus Verilog
$end
$timescale
	1ps
$end
$scope module data_memory_tb $end
$var wire 32 ! read_data [31:0] $end
$var reg 1 " MemRead $end
$var reg 1 # MemWrite $end
$var reg 32 $ address [31:0] $end
$var reg 1 % clk $end
$var reg 32 & write_data [31:0] $end
$scope module uut $end
$var wire 1 " MemRead $end
$var wire 1 # MemWrite $end
$var wire 32 ' address [31:0] $end
$var wire 1 % clk $end
$var wire 32 ( read_data [31:0] $end
$var wire 32 ) write_data [31:0] $end
$upscope $end
$upscope $end
$enddefinitions $end
$comment Show the parameter values. $end
$dumpall
$end
#0
$dumpvars
b0 )
bx (
b0 '
b0 &
0%
b0 $
0#
0"
bx !
$end
#5
1%
#10
0%
b10101010101010101010101010101010 &
b10101010101010101010101010101010 )
b100 $
b100 '
1#
#15
b10101010101010101010101010101010 !
b10101010101010101010101010101010 (
1%
#20
bx !
bx (
0%
b10111011101110111011101110111011 &
b10111011101110111011101110111011 )
b1000 $
b1000 '
#25
b10111011101110111011101110111011 !
b10111011101110111011101110111011 (
1%
#30
0%
0#
#35
1%
#40
b10101010101010101010101010101010 !
b10101010101010101010101010101010 (
0%
b100 $
b100 '
1"
#45
b10111011101110111011101110111011 !
b10111011101110111011101110111011 (
1%
b1000 $
b1000 '
#50
bx !
bx (
0%
b1100 $
b1100 '
