params.vh
// Largura de dados e endereço
`define DATA_WIDTH  32
`define ADDR_WIDTH  32

`define ZERO        32'b0;

// Definições da memoria de instruções
`define INST_MEM_DEPTH 256
`define INST_MEM_FILE "../../program.bin"

// Definições do branco de registradores
`define NUM_REGISTERS 32
`define REG_ADDR_WIDTH 5 // log_2(NUM_REGISTERS)

// Definições da ALU
`define ALU_OP_WIDTH = 4

// operações da ALU
`define ALU_ADD   4'b0000
`define ALU_SUB   4'b0001
`define ALU_AND   4'b0010
`define ALU_OR    4'b0011
`define ALU_XOR   4'b0100
`define ALU_SLL   4'b0101
`define ALU_SRL   4'b0110

// Definições da unidade de controle

// pag 126
`define OPCODE_R_TYPE  7'b0110011
`define OPCODE_I_TYPE  7'b0010011
`define OPCODE_LOAD    7'b0000011
`define OPCODE_STORE   7'b0100011
`define OPCODE_BRANCH  7'b1100111

// Definição da memoria de dados
`define DMEM_DEPTH   256 
`define DATA_FILE    "../../data.bin"

risc_v_blocks/register_file/register_file.v
`include "../../params.vh"

module register_file(
  input clk,
  input rst,
  input reg_write,

  input [`REG_ADDR_WIDTH-1:0] read_address_a,
  input [`REG_ADDR_WIDTH-1:0] read_address_b,
  input [`REG_ADDR_WIDTH-1:0] write_address,

  input [`DATA_WIDTH-1:0] write_data,

  output reg [`DATA_WIDTH-1:0] read_data_a,
  output reg [`DATA_WIDTH-1:0] read_data_b
);
  reg [`DATA_WIDTH-1:0] registers [`NUM_REGISTERS-1:0];

  integer i = 0;

  always @(posedge clk or posedge rst) begin
    if (rst) begin
      
      for (i = 0; i < `NUM_REGISTERS; i = i + 1) begin
        registers[i] <= `DATA_WIDTH'b0;
      end
    end else if (reg_write && write_address != `REG_ADDR_WIDTH'b0) begin
      registers[write_address] <= write_data;
    end
  end

  always @(*) begin
    read_data_a = (read_address_a == 5'b0) ? 32'b0 : registers[read_address_a];
    read_data_b = (read_address_b == 5'b0) ? 32'b0 : registers[read_address_b];
  end

endmodule

risc_v_blocks/register_file/register_file_tb.v
`timescale 1ps/1ps
`include "../../params.vh"

module register_file_tb();
  reg clk = 0;
  always #5 clk = ~clk;

  reg rst = 1;
  reg reg_write = 0;
  reg [`REG_ADDR_WIDTH-1:0] read_address_a = 0;
  reg [`REG_ADDR_WIDTH-1:0] read_address_b = 0;
  reg [`REG_ADDR_WIDTH-1:0] write_address = 0;

  reg [`DATA_WIDTH-1:0] write_data = 0;

  wire [`DATA_WIDTH-1:0] read_data_a;
  wire [`DATA_WIDTH-1:0] read_data_b;

  register_file uut (
    .clk(clk),
    .rst(rst),
    .reg_write(reg_write),
    .read_address_a(read_address_a),
    .read_address_b(read_address_b),
    .write_address(write_address),
    .write_data(write_data),
    .read_data_a(read_data_a),
    .read_data_b(read_data_b)
  );

  initial begin 
    $dumpfile("register_file_tb.vcd");
    $dumpvars(0, register_file_tb);

    // Finaliza o reset do banco de registradores
    #10
    rst = 0;

    // Escreve 123 no registrador 1
    #10
    write_address = `REG_ADDR_WIDTH'd1;
    write_data = `DATA_WIDTH'd123;
    reg_write = 1;
    #10
    reg_write = 0;

    // Lê o valor do registrador 1;
    read_address_a = `REG_ADDR_WIDTH'd1;
    #5;
    $display("Esperado: 123, Lido: %d", read_data_a);

    // Tenta escrever 99 no registrador 0
    write_address = `REG_ADDR_WIDTH'd0;
    write_data = `DATA_WIDTH'd99;
    reg_write = 1;
    #10
    reg_write = 0;

    #10
    read_address_a = `REG_ADDR_WIDTH'd0;
    #5
    $display("Esperado: 0, Lido: %d", read_data_a);

    // Escrever 736 no registrador 2
    write_address = `REG_ADDR_WIDTH'd2;
    write_data = `DATA_WIDTH'd736;
    reg_write = 1;
    #10;
    reg_write = 0;

    // Ler registradores 1 e 2 simultaneamente
    read_address_a = `REG_ADDR_WIDTH'd1;
    read_address_b = `REG_ADDR_WIDTH'd2;
    #5;
    $display("Lido A: %d (esperado 123), Lido B: %d (esperado 736)", read_data_a, read_data_b);

    #20 $finish;
  end

endmodule

risc_v_blocks/register_file/register_file_tb.vcd
$date
	Sun Jul 06 00:16:27 2025
$end
$version
	Icarus Verilog
$end
$timescale
	1ps
$end
$scope module register_file_tb $end
$var wire 32 ! read_data_b [31:0] $end
$var wire 32 " read_data_a [31:0] $end
$var reg 1 # clk $end
$var reg 5 $ read_address_a [4:0] $end
$var reg 5 % read_address_b [4:0] $end
$var reg 1 & reg_write $end
$var reg 1 ' rst $end
$var reg 5 ( write_address [4:0] $end
$var reg 32 ) write_data [31:0] $end
$scope module uut $end
$var wire 1 # clk $end
$var wire 5 * read_address_a [4:0] $end
$var wire 5 + read_address_b [4:0] $end
$var wire 1 & reg_write $end
$var wire 1 ' rst $end
$var wire 5 , write_address [4:0] $end
$var wire 32 - write_data [31:0] $end
$var reg 32 . read_data_a [31:0] $end
$var reg 32 / read_data_b [31:0] $end
$var integer 32 0 i [31:0] $end
$upscope $end
$upscope $end
$enddefinitions $end
$comment Show the parameter values. $end
$dumpall
$end
#0
$dumpvars
b100000 0
b0 /
b0 .
b0 -
b0 ,
b0 +
b0 *
b0 )
b0 (
1'
0&
b0 %
b0 $
0#
b0 "
b0 !
$end
#5
b100000 0
1#
#10
0#
0'
#15
1#
#20
0#
1&
b1111011 )
b1111011 -
b1 (
b1 ,
#25
1#
#30
b1111011 "
b1111011 .
0#
b1 $
b1 *
0&
#35
1#
1&
b1100011 )
b1100011 -
b0 (
b0 ,
#40
0#
#45
1#
0&
#50
0#
#55
b0 "
b0 .
1#
b0 $
b0 *
#60
0#
1&
b1011100000 )
b1011100000 -
b10 (
b10 ,
#65
1#
#70
b1011100000 !
b1011100000 /
b1111011 "
b1111011 .
0#
b10 %
b10 +
b1 $
b1 *
0&
