instruction_memory/instruction_memory.v
module instruction_memory (
  input  [31:0] read_address,
  output [31:0] instruction_data
);
  // Crie uma memoria de instruções com 256 palavras de 32 bits
  reg [31:0] memory [0:255];

  initial begin
    // Carrega o arquivo contendo o programa para a memoria de intruções
    $readmemh("../program.hex", memory);
  end

  // Atribui o valor da memória ao dado de instrução
  assign instruction_data = memory[read_address[31:2]];

endmodule

instruction_memory/instruction_memory_tb.v
`timescale 1ns / 1ps

module instruction_memory_tb;

  reg [31:0] addr;
  wire [31:0] instr;

  instruction_memory uut (
    .read_address(addr),
    .instruction_data(instr)
  );

  integer i;

  initial begin
    $dumpfile("instruction_memory_tb.vcd");
    $dumpvars(0, instruction_memory_tb);
    

    for (i = 0; i < 10; i = i + 1) begin
      addr = i * 4;
      #10;
      $display("Endereco: %h, Instrucao: %b", addr, instr);
    end
    
    #10 $finish;
  end

endmodule

instruction_memory/instruction_memory_tb.vcd
$date
	Sat Jul 05 17:43:45 2025
$end
$version
	Icarus Verilog
$end
$timescale
	1ps
$end
$scope module instruction_memory_tb $end
$var wire 32 ! instr [31:0] $end
$var reg 32 " addr [31:0] $end
$var integer 32 # i [31:0] $end
$scope module uut $end
$var wire 32 $ instruction_data [31:0] $end
$var wire 32 % read_address [31:0] $end
$upscope $end
$upscope $end
$enddefinitions $end
$comment Show the parameter values. $end
$dumpall
$end
#0
$dumpvars
b0 %
b10010011 $
b0 #
b0 "
b10010011 !
$end
#10000
b100000000000100010011 !
b100000000000100010011 $
b100 "
b100 %
b1 #
#20000
b1000001000000110110011 !
b1000001000000110110011 $
b1000 "
b1000 %
b10 #
#30000
b1100010000000100010011 !
b1100010000000100010011 $
b1100 "
b1100 %
b11 #
#40000
bx !
bx $
b10000 "
b10000 %
b100 #
#50000
b10100 "
b10100 %
b101 #
#60000
b11000 "
b11000 %
b110 #
#70000
b11100 "
b11100 %
b111 #
#80000
b100000 "
b100000 %
b1000 #
#90000
b100100 "
b100100 %
b1001 #
#100000
b1010 #
